{
  "sites": [
    {
      "id": "f0402323-9236-4b79-8c32-63294f0d2d21",
      "key": "155",
      "name": "155",
      "api": "https://155api.com/api.php/provide/vod",
      "type": 2,
      "isActive": 1,
      "time": "2026-07-06T20:02:42.701Z",
      "isDefault": 0,
      "remark": "speed:43ms",
      "tags": [],
      "priority": 0,
      "proxyMode": "none",
      "customProxy": ""
    },
    {
      "id": "c604c8aa-958a-406f-8e50-74bafcdb7621",
      "key": "步步高资源",
      "name": "步步高资源",
      "api": "https://api.yparse.com/api/json",
      "type": 2,
      "isActive": 1,
      "time": "2026-07-06T20:02:42.701Z",
      "isDefault": 0,
      "remark": "speed:47ms",
      "tags": [],
      "priority": 0,
      "proxyMode": "none",
      "customProxy": ""
    },
    {
      "id": "46a1a3ad-4320-4a71-988f-d396fc266a0a",
      "key": "jkun",
      "name": "jkun",
      "api": "https://jkunzyapi.com/api.php/provide/vod",
      "type": 2,
      "isActive": 1,
      "time": "2026-07-06T20:02:42.701Z",
      "isDefault": 0,
      "remark": "speed:68ms",
      "tags": [],
      "priority": 0,
      "proxyMode": "none",
      "customProxy": ""
    },
    {
      "id": "a6768137-12e0-4c9d-8c41-29c404d5d008",
      "key": "极速资源",
      "name": "极速资源",
      "api": "https://jszyapi.com/api.php/provide/vod",
      "type": 2,
      "isActive": 1,
      "time": "2026-07-06T20:02:42.701Z",
      "isDefault": 0,
      "remark": "speed:78ms",
      "tags": [],
      "priority": 0,
      "proxyMode": "none",
      "customProxy": ""
    },
    {
      "id": "5ec9fc23-1e3a-4d06-90f3-a6be756adf14",
      "key": "光速HTTP",
      "name": "光速HTTP",
      "api": "http://api.guangsuapi.com/api.php/provide/vod",
      "type": 2,
      "isActive": 1,
      "time": "2026-07-06T20:02:42.701Z",
      "isDefault": 0,
      "remark": "speed:78ms",
      "tags": [],
      "priority": 0,
      "proxyMode": "none",
      "customProxy": ""
    },
    {
      "id": "dbec2adf-835e-40e8-8f28-c9a6f6e1c3d1",
      "key": "索尼资源",
      "name": "索尼资源",
      "api": "https://suoniapi.com/api.php/provide/vod",
      "type": 2,
      "isActive": 1,
      "time": "2026-07-06T20:02:42.701Z",
      "isDefault": 0,
      "remark": "speed:83ms",
      "tags": [],
      "priority": 0,
      "proxyMode": "none",
      "customProxy": ""
    },
    {
      "id": "de9c5b14-a8b1-4cd9-97ce-be1fe0ff63b2",
      "key": "百度云资源",
      "name": "百度云资源",
      "api": "https://api.apibdzy.com/api.php/provide/vod",
      "type": 2,
      "isActive": 1,
      "time": "2026-07-06T20:02:42.701Z",
      "isDefault": 0,
      "remark": "speed:84ms",
      "tags": [],
      "priority": 0,
      "proxyMode": "none",
      "customProxy": ""
    },
    {
      "id": "74798c0a-9570-447c-919f-12ec987f390b",
      "key": "爱蛋资源",
      "name": "爱蛋资源",
      "api": "https://lovedan.net/api.php/provide/vod",
      "type": 2,
      "isActive": 1,
      "time": "2026-07-06T20:02:42.701Z",
      "isDefault": 0,
      "remark": "speed:104ms",
      "tags": [],
      "priority": 0,
      "proxyMode": "none",
      "customProxy": ""
    },
    {
      "id": "37c082b4-eb0b-4ce8-9499-f45fb17a9741",
      "key": "金鹰点播",
      "name": "金鹰点播",
      "api": "https://jinyingzy.com/api.php/provide/vod",
      "type": 2,
      "isActive": 1,
      "time": "2026-07-06T20:02:42.701Z",
      "isDefault": 0,
      "remark": "speed:104ms",
      "tags": [],
      "priority": 0,
      "proxyMode": "none",
      "customProxy": ""
    },
    {
      "id": "03cb83f8-26b0-441d-9103-341b978efd04",
      "key": "🎧全网┃音乐",
      "name": "🎧全网┃音乐",
      "api": "https://16409.kstore.vip/js/%E5%93%94%E5%93%A9MTV.json",
      "type": 2,
      "isActive": 1,
      "time": "2026-07-06T20:02:42.701Z",
      "isDefault": 0,
      "remark": "speed:118ms",
      "tags": [],
      "priority": 0,
      "proxyMode": "none",
      "customProxy": ""
    },
    {
      "id": "6d5b1818-0ed2-45ec-a52b-ea7efec6da85",
      "key": "最大资源",
      "name": "最大资源",
      "api": "https://api.zuidapi.com/api.php/provide/vod",
      "type": 2,
      "isActive": 1,
      "time": "2026-07-06T20:02:42.701Z",
      "isDefault": 0,
      "remark": "speed:119ms",
      "tags": [],
      "priority": 0,
      "proxyMode": "none",
      "customProxy": ""
    },
    {
      "id": "508ad292-e267-478b-aad8-6a9c3dc8b72f",
      "key": "🪔聚合┃短剧",
      "name": "🪔聚合┃短剧",
      "api": "https://16409.kstore.vip/js/%E8%81%9A%E5%90%88%E7%9F%AD%E5%89%A7.js",
      "type": 2,
      "isActive": 1,
      "time": "2026-07-06T20:02:42.701Z",
      "isDefault": 0,
      "remark": "speed:129ms",
      "tags": [],
      "priority": 0,
      "proxyMode": "none",
      "customProxy": ""
    },
    {
      "id": "300cdefc-73e2-4c1c-9924-d1c3db13f2ea",
      "key": "黄色仓库",
      "name": "黄色仓库",
      "api": "https://hsckzy.vip/api.php/provide/vod",
      "type": 2,
      "isActive": 1,
      "time": "2026-07-06T20:02:42.701Z",
      "isDefault": 0,
      "remark": "speed:133ms",
      "tags": [],
      "priority": 0,
      "proxyMode": "none",
      "customProxy": ""
    },
    {
      "id": "3ee38151-63fd-4080-9c0c-0d01ffc960c8",
      "key": "无尽ME",
      "name": "无尽ME",
      "api": "https://api.wujinapi.me/api.php/provide/vod",
      "type": 2,
      "isActive": 1,
      "time": "2026-07-06T20:02:42.701Z",
      "isDefault": 0,
      "remark": "speed:137ms",
      "tags": [],
      "priority": 0,
      "proxyMode": "none",
      "customProxy": ""
    },
    {
      "id": "a5021bd8-f566-4a97-b2be-3c80473666e3",
      "key": "🥅企鹅┃体育直播",
      "name": "🥅企鹅┃体育直播",
      "api": "https://16409.kstore.vip/js/%E4%BC%81%E9%B9%85%E7%9B%B4%E6%92%AD.json",
      "type": 2,
      "isActive": 1,
      "time": "2026-07-06T20:02:42.701Z",
      "isDefault": 0,
      "remark": "speed:137ms",
      "tags": [],
      "priority": 0,
      "proxyMode": "none",
      "customProxy": ""
    },
    {
      "id": "35e1f5a8-bc02-4da2-88bb-fb688c481161",
      "key": "乐子HTTP",
      "name": "乐子HTTP",
      "api": "http://cj.lziapi.com/api.php/provide/vod",
      "type": 2,
      "isActive": 1,
      "time": "2026-07-06T20:02:42.701Z",
      "isDefault": 0,
      "remark": "speed:139ms",
      "tags": [],
      "priority": 0,
      "proxyMode": "none",
      "customProxy": ""
    },
    {
      "id": "07779f3c-3ede-4187-bf29-88b8a1a4a66d",
      "key": "虎牙资源",
      "name": "虎牙资源",
      "api": "https://www.huyaapi.com/api.php/provide/vod",
      "type": 2,
      "isActive": 1,
      "time": "2026-07-06T20:02:42.701Z",
      "isDefault": 0,
      "remark": "speed:147ms",
      "tags": [],
      "priority": 0,
      "proxyMode": "none",
      "customProxy": ""
    },
    {
      "id": "1caa08e4-69b5-4a80-90a8-31cdfa0d2995",
      "key": "玉兔",
      "name": "玉兔",
      "api": "https://yutuzy10.com/api.php/provide/vod",
      "type": 2,
      "isActive": 1,
      "time": "2026-07-06T20:02:42.701Z",
      "isDefault": 0,
      "remark": "speed:164ms",
      "tags": [],
      "priority": 0,
      "proxyMode": "none",
      "customProxy": ""
    },
    {
      "id": "00f090f4-a61d-48a9-983d-841f2b049ef1",
      "key": "CK",
      "name": "CK",
      "api": "https://www.ckzy1.com/api.php/provide/vod",
      "type": 2,
      "isActive": 1,
      "time": "2026-07-06T20:02:42.701Z",
      "isDefault": 0,
      "remark": "speed:184ms",
      "tags": [],
      "priority": 0,
      "proxyMode": "none",
      "customProxy": ""
    },
    {
      "id": "5ea1f080-341f-4117-8c41-d85d2dc4abe0",
      "key": "新浪资源",
      "name": "新浪资源",
      "api": "http://api.xinlangapi.com/xinlangapi.php/provide/vod",
      "type": 2,
      "isActive": 1,
      "time": "2026-07-06T20:02:42.701Z",
      "isDefault": 0,
      "remark": "speed:196ms",
      "tags": [],
      "priority": 0,
      "proxyMode": "none",
      "customProxy": ""
    },
    {
      "id": "80f0ca00-9c37-4e49-8a81-c7f7dac6f5b3",
      "key": "小鸡资源",
      "name": "小鸡资源",
      "api": "https://api.xiaojizy.live/provide/vod",
      "type": 2,
      "isActive": 1,
      "time": "2026-07-06T20:02:42.701Z",
      "isDefault": 0,
      "remark": "speed:196ms",
      "tags": [],
      "priority": 0,
      "proxyMode": "none",
      "customProxy": ""
    },
    {
      "id": "54f80b3e-ed2f-456c-a99d-76ea52570a3b",
      "key": "鲸鱼资源",
      "name": "鲸鱼资源",
      "api": "https://jyzyapi.com/provide/vod",
      "type": 2,
      "isActive": 1,
      "time": "2026-07-06T20:02:42.701Z",
      "isDefault": 0,
      "remark": "speed:206ms",
      "tags": [],
      "priority": 0,
      "proxyMode": "none",
      "customProxy": ""
    },
    {
      "id": "0fbbf4c7-a3fd-4a83-93b5-f34f21800089",
      "key": "丫丫点播",
      "name": "丫丫点播",
      "api": "https://cj.yayazy.net/api.php/provide/vod",
      "type": 2,
      "isActive": 1,
      "time": "2026-07-06T20:02:42.701Z",
      "isDefault": 0,
      "remark": "speed:207ms",
      "tags": [],
      "priority": 0,
      "proxyMode": "none",
      "customProxy": ""
    },
    {
      "id": "9b622ed3-4234-454c-a5ca-bf81b8a5d2ce",
      "key": "索尼-闪电",
      "name": "索尼-闪电",
      "api": "https://xsd.sdzyapi.com/api.php/provide/vod",
      "type": 2,
      "isActive": 1,
      "time": "2026-07-06T20:02:42.701Z",
      "isDefault": 0,
      "remark": "speed:236ms",
      "tags": [],
      "priority": 0,
      "proxyMode": "none",
      "customProxy": ""
    },
    {
      "id": "9b629dcd-96da-40ef-9119-3cd3dea3c924",
      "key": "无尽CC",
      "name": "无尽CC",
      "api": "https://api.wujinapi.cc/api.php/provide/vod",
      "type": 2,
      "isActive": 1,
      "time": "2026-07-06T20:02:42.701Z",
      "isDefault": 0,
      "remark": "speed:253ms",
      "tags": [],
      "priority": 0,
      "proxyMode": "none",
      "customProxy": ""
    },
    {
      "id": "11da7787-5667-428f-b60d-1e2227b7a675",
      "key": "红牛资源",
      "name": "红牛资源",
      "api": "https://www.hongniuzy2.com/api.php/provide/vod",
      "type": 2,
      "isActive": 1,
      "time": "2026-07-06T20:02:42.701Z",
      "isDefault": 0,
      "remark": "speed:255ms",
      "tags": [],
      "priority": 0,
      "proxyMode": "none",
      "customProxy": ""
    },
    {
      "id": "642411b0-89ac-4b53-a9fa-c05013c275ef",
      "key": "新浪HTTPS",
      "name": "新浪HTTPS",
      "api": "https://api.xinlangapi.com/xinlangapi.php/provide/vod",
      "type": 2,
      "isActive": 1,
      "time": "2026-07-06T20:02:42.701Z",
      "isDefault": 0,
      "remark": "speed:255ms",
      "tags": [],
      "priority": 0,
      "proxyMode": "none",
      "customProxy": ""
    },
    {
      "id": "3fe39853-3978-4d0b-9a81-bb46773ef804",
      "key": "牛牛点播",
      "name": "牛牛点播",
      "api": "https://api.niuniuzy.me/api.php/provide/vod",
      "type": 2,
      "isActive": 1,
      "time": "2026-07-06T20:02:42.701Z",
      "isDefault": 0,
      "remark": "speed:256ms",
      "tags": [],
      "priority": 0,
      "proxyMode": "none",
      "customProxy": ""
    },
    {
      "id": "93c29f7a-b12d-49b6-9204-e1cf7c07ebea",
      "key": "海豚资源",
      "name": "海豚资源",
      "api": "https://hhzyapi.com/api.php/provide/vod",
      "type": 2,
      "isActive": 1,
      "time": "2026-07-06T20:02:42.701Z",
      "isDefault": 0,
      "remark": "speed:261ms",
      "tags": [],
      "priority": 0,
      "proxyMode": "none",
      "customProxy": ""
    },
    {
      "id": "b102da8c-1a53-40f3-98fc-d20d9c76cc10",
      "key": "天涯资源",
      "name": "天涯资源",
      "api": "https://tyyszy.com/api.php/provide/vod",
      "type": 2,
      "isActive": 1,
      "time": "2026-07-06T20:02:42.701Z",
      "isDefault": 0,
      "remark": "speed:264ms",
      "tags": [],
      "priority": 0,
      "proxyMode": "none",
      "customProxy": ""
    },
    {
      "id": "eb748e30-fd9c-4a9b-9c17-946e2abdba95",
      "key": "最大点播",
      "name": "最大点播",
      "api": "http://zuidazy.me/api.php/provide/vod",
      "type": 2,
      "isActive": 1,
      "time": "2026-07-06T20:02:42.701Z",
      "isDefault": 0,
      "remark": "speed:273ms",
      "tags": [],
      "priority": 0,
      "proxyMode": "none",
      "customProxy": ""
    },
    {
      "id": "d2fffcc2-fbed-43fb-b641-cf39467bd940",
      "key": "lsb",
      "name": "lsb",
      "api": "https://apilsbzy1.com/api.php/provide/vod",
      "type": 2,
      "isActive": 1,
      "time": "2026-07-06T20:02:42.701Z",
      "isDefault": 0,
      "remark": "speed:274ms",
      "tags": [],
      "priority": 0,
      "proxyMode": "none",
      "customProxy": ""
    },
    {
      "id": "387bd624-284f-4014-aa35-5e470c617695",
      "key": "暴风APP",
      "name": "暴风APP",
      "api": "https://app.bfzyapi.com/api.php/provide/vod",
      "type": 2,
      "isActive": 1,
      "time": "2026-07-06T20:02:42.701Z",
      "isDefault": 0,
      "remark": "speed:279ms",
      "tags": [],
      "priority": 0,
      "proxyMode": "none",
      "customProxy": ""
    },
    {
      "id": "7c63cedf-e24b-4ff0-a2a9-e1a473f7c5f2",
      "key": "U酷资源88",
      "name": "U酷资源88",
      "api": "https://api.ukuapi88.com/api.php/provide/vod",
      "type": 2,
      "isActive": 1,
      "time": "2026-07-06T20:02:42.701Z",
      "isDefault": 0,
      "remark": "speed:301ms",
      "tags": [],
      "priority": 0,
      "proxyMode": "none",
      "customProxy": ""
    },
    {
      "id": "670fd12b-771a-4bfa-b5e4-c16dc5db223b",
      "key": "黄AV资源站",
      "name": "黄AV资源站",
      "api": "https://www.pgxdy.com/api/json.php",
      "type": 2,
      "isActive": 1,
      "time": "2026-07-06T20:02:42.701Z",
      "isDefault": 0,
      "remark": "speed:305ms",
      "tags": [],
      "priority": 0,
      "proxyMode": "none",
      "customProxy": ""
    },
    {
      "id": "c855558b-f782-4b82-b2d1-51f3796949b2",
      "key": "閃電资源",
      "name": "閃電资源",
      "api": "https://sdzyapi.com/api.php/provide/vod",
      "type": 2,
      "isActive": 1,
      "time": "2026-07-06T20:02:42.701Z",
      "isDefault": 0,
      "remark": "speed:320ms",
      "tags": [],
      "priority": 0,
      "proxyMode": "none",
      "customProxy": ""
    },
    {
      "id": "5d82fbd4-77c2-43f1-b351-7efc409a7656",
      "key": "iKun资源",
      "name": "iKun资源",
      "api": "https://ikunzyapi.com/api.php/provide/vod",
      "type": 2,
      "isActive": 1,
      "time": "2026-07-06T20:02:42.701Z",
      "isDefault": 0,
      "remark": "speed:323ms",
      "tags": [],
      "priority": 0,
      "proxyMode": "none",
      "customProxy": ""
    },
    {
      "id": "983a42d4-c45c-4afe-9c91-de2d82ebcbaa",
      "key": "无尽NET",
      "name": "无尽NET",
      "api": "https://api.wujinapi.net/api.php/provide/vod",
      "type": 2,
      "isActive": 1,
      "time": "2026-07-06T20:02:42.701Z",
      "isDefault": 0,
      "remark": "speed:327ms",
      "tags": [],
      "priority": 0,
      "proxyMode": "none",
      "customProxy": ""
    },
    {
      "id": "fc79ae44-c9b0-4cef-be25-8a6bcbeb856e",
      "key": "天涯海角",
      "name": "天涯海角",
      "api": "https://tyyszyapi.com/api.php/provide/vod",
      "type": 2,
      "isActive": 1,
      "time": "2026-07-06T20:02:42.701Z",
      "isDefault": 0,
      "remark": "speed:344ms",
      "tags": [],
      "priority": 0,
      "proxyMode": "none",
      "customProxy": ""
    },
    {
      "id": "67b14ceb-2558-4971-99bf-290aa4d9e309",
      "key": "百万资源",
      "name": "百万资源",
      "api": "https://api.bwzyz.com/api.php/provide/vod",
      "type": 2,
      "isActive": 1,
      "time": "2026-07-06T20:02:42.701Z",
      "isDefault": 0,
      "remark": "speed:377ms",
      "tags": [],
      "priority": 0,
      "proxyMode": "none",
      "customProxy": ""
    },
    {
      "id": "edd53d27-7eae-4295-8b45-96cf5b8c1e09",
      "key": "无尽资源",
      "name": "无尽资源",
      "api": "https://api.wujinapi.com/api.php/provide/vod",
      "type": 2,
      "isActive": 1,
      "time": "2026-07-06T20:02:42.701Z",
      "isDefault": 0,
      "remark": "speed:387ms",
      "tags": [],
      "priority": 0,
      "proxyMode": "none",
      "customProxy": ""
    },
    {
      "id": "722f8a67-d0ef-4e54-926f-8512fe4f1467",
      "key": "樱花资源",
      "name": "樱花资源",
      "api": "https://m3u8.apiyhzy.com/api.php/provide/vod",
      "type": 2,
      "isActive": 1,
      "time": "2026-07-06T20:02:42.701Z",
      "isDefault": 0,
      "remark": "speed:397ms",
      "tags": [],
      "priority": 0,
      "proxyMode": "none",
      "customProxy": ""
    },
    {
      "id": "d3d94315-9c56-409e-aa81-3cf24dfd16b5",
      "key": "飘零资源",
      "name": "飘零资源",
      "api": "https://p2100.net/api.php/provide/vod",
      "type": 2,
      "isActive": 1,
      "time": "2026-07-06T20:02:42.701Z",
      "isDefault": 0,
      "remark": "speed:397ms",
      "tags": [],
      "priority": 0,
      "proxyMode": "none",
      "customProxy": ""
    },
    {
      "id": "a376e521-9f96-476b-8344-2a3a3e24e04b",
      "key": "乐播资源",
      "name": "乐播资源",
      "api": "https://lbapi9.com/api.php/provide/vod",
      "type": 2,
      "isActive": 1,
      "time": "2026-07-06T20:02:42.701Z",
      "isDefault": 0,
      "remark": "speed:399ms",
      "tags": [],
      "priority": 0,
      "proxyMode": "none",
      "customProxy": ""
    },
    {
      "id": "12a09ff1-9c9a-458f-9b38-f8aa674b72cf",
      "key": "美少女资源站",
      "name": "美少女资源站",
      "api": "https://www.msnii.com/api/json.php",
      "type": 2,
      "isActive": 1,
      "time": "2026-07-06T20:02:42.701Z",
      "isDefault": 0,
      "remark": "speed:413ms",
      "tags": [],
      "priority": 0,
      "proxyMode": "none",
      "customProxy": ""
    },
    {
      "id": "46bf06bc-5219-477d-aff2-dbafc112c42f",
      "key": "细胞采集",
      "name": "细胞采集",
      "api": "https://www.xxibaozyw.com/api.php/provide/vod",
      "type": 2,
      "isActive": 1,
      "time": "2026-07-06T20:02:42.701Z",
      "isDefault": 0,
      "remark": "speed:418ms",
      "tags": [],
      "priority": 0,
      "proxyMode": "none",
      "customProxy": ""
    },
    {
      "id": "19383b87-580a-48f7-9066-cb4c1a162b51",
      "key": "乐子资源",
      "name": "乐子资源",
      "api": "https://cj.lziapi.com/api.php/provide/vod",
      "type": 2,
      "isActive": 1,
      "time": "2026-07-06T20:02:42.701Z",
      "isDefault": 0,
      "remark": "speed:429ms",
      "tags": [],
      "priority": 0,
      "proxyMode": "none",
      "customProxy": ""
    },
    {
      "id": "f7f797e5-4131-40ae-858c-c0f7619c74eb",
      "key": "淫水机资源站",
      "name": "淫水机资源站",
      "api": "https://www.xrbsp.com/api/json.php",
      "type": 2,
      "isActive": 1,
      "time": "2026-07-06T20:02:42.701Z",
      "isDefault": 0,
      "remark": "speed:431ms",
      "tags": [],
      "priority": 0,
      "proxyMode": "none",
      "customProxy": ""
    },
    {
      "id": "9ea6dd73-8db8-4068-b0bb-b33fca676855",
      "key": "红牛资源3",
      "name": "红牛资源3",
      "api": "https://www.hongniuzy3.com/api.php/provide/vod",
      "type": 2,
      "isActive": 1,
      "time": "2026-07-06T20:02:42.701Z",
      "isDefault": 0,
      "remark": "speed:455ms",
      "tags": [],
      "priority": 0,
      "proxyMode": "none",
      "customProxy": ""
    },
    {
      "id": "bc86e062-800e-45fd-8752-aa92bcba74ad",
      "key": "香奶儿资源站",
      "name": "香奶儿资源站",
      "api": "https://www.gdlsp.com/api/json.php",
      "type": 2,
      "isActive": 1,
      "time": "2026-07-06T20:02:42.701Z",
      "isDefault": 0,
      "remark": "speed:460ms",
      "tags": [],
      "priority": 0,
      "proxyMode": "none",
      "customProxy": ""
    },
    {
      "id": "fc994f97-b166-4474-858f-0a3c589fbd4b",
      "key": "豆瓣资源",
      "name": "豆瓣资源",
      "api": "https://dbzy.tv/api.php/provide/vod",
      "type": 2,
      "isActive": 1,
      "time": "2026-07-06T20:02:42.701Z",
      "isDefault": 0,
      "remark": "speed:463ms",
      "tags": [],
      "priority": 0,
      "proxyMode": "none",
      "customProxy": ""
    },
    {
      "id": "183070ad-7ba4-468f-9919-d3cccc800fdc",
      "key": "优酷资源",
      "name": "优酷资源",
      "api": "https://api.ukuapi.com/api.php/provide/vod",
      "type": 2,
      "isActive": 1,
      "time": "2026-07-06T20:02:42.701Z",
      "isDefault": 0,
      "remark": "speed:498ms",
      "tags": [],
      "priority": 0,
      "proxyMode": "none",
      "customProxy": ""
    },
    {
      "id": "20cf6680-5b97-4ed0-8460-709802ff3d9c",
      "key": "旺旺资源",
      "name": "旺旺资源",
      "api": "https://wwzy.tv/api.php/provide/vod",
      "type": 2,
      "isActive": 1,
      "time": "2026-07-06T20:02:42.701Z",
      "isDefault": 0,
      "remark": "speed:505ms",
      "tags": [],
      "priority": 0,
      "proxyMode": "none",
      "customProxy": ""
    },
    {
      "id": "2f0734f0-6669-430b-974b-b9603d8c9b33",
      "key": "🧲磁力在线┃原盘",
      "name": "🧲磁力在线┃原盘",
      "api": "https://16409.kstore.vip/js/dyg.json",
      "type": 2,
      "isActive": 1,
      "time": "2026-07-06T20:02:42.701Z",
      "isDefault": 0,
      "remark": "speed:530ms",
      "tags": [],
      "priority": 0,
      "proxyMode": "none",
      "customProxy": ""
    },
    {
      "id": "ab67cffd-0f8e-46a3-81c6-1497e667c56b",
      "key": "卧龙资源",
      "name": "卧龙资源",
      "api": "https://wolongzyw.com/api.php/provide/vod",
      "type": 2,
      "isActive": 1,
      "time": "2026-07-06T20:02:42.701Z",
      "isDefault": 0,
      "remark": "speed:570ms",
      "tags": [],
      "priority": 0,
      "proxyMode": "none",
      "customProxy": ""
    },
    {
      "id": "49ebeffd-723d-4ef5-b9d0-1bcefb095121",
      "key": "白嫖资源站",
      "name": "白嫖资源站",
      "api": "https://www.kxgav.com/api/json.php",
      "type": 2,
      "isActive": 1,
      "time": "2026-07-06T20:02:42.701Z",
      "isDefault": 0,
      "remark": "speed:570ms",
      "tags": [],
      "priority": 0,
      "proxyMode": "none",
      "customProxy": ""
    },
    {
      "id": "0c8d4ca5-9cb6-466b-bfe8-11be8820aeeb",
      "key": "旺旺API",
      "name": "旺旺API",
      "api": "https://api.wwzy.tv/api.php/provide/vod",
      "type": 2,
      "isActive": 1,
      "time": "2026-07-06T20:02:42.701Z",
      "isDefault": 0,
      "remark": "speed:591ms",
      "tags": [],
      "priority": 0,
      "proxyMode": "none",
      "customProxy": ""
    },
    {
      "id": "57171cb0-94ff-4a65-9315-6b944b7cbbfc",
      "key": "番号资源",
      "name": "番号资源",
      "api": "http://fhapi9.com/api.php/provide/vod",
      "type": 2,
      "isActive": 1,
      "time": "2026-07-06T20:02:42.701Z",
      "isDefault": 0,
      "remark": "speed:591ms",
      "tags": [],
      "priority": 0,
      "proxyMode": "none",
      "customProxy": ""
    },
    {
      "id": "746bb1fa-baa6-43dc-b4ca-acc17d588b47",
      "key": "卧龙采集",
      "name": "卧龙采集",
      "api": "https://collect.wolongzyw.com/api.php/provide/vod",
      "type": 2,
      "isActive": 1,
      "time": "2026-07-06T20:02:42.701Z",
      "isDefault": 0,
      "remark": "speed:603ms",
      "tags": [],
      "priority": 0,
      "proxyMode": "none",
      "customProxy": ""
    },
    {
      "id": "c7b0debb-df2e-44c7-ba2b-6e5f88c1b207",
      "key": "非凡线路1",
      "name": "非凡线路1",
      "api": "http://ffzy1.tv/api.php/provide/vod",
      "type": 2,
      "isActive": 1,
      "time": "2026-07-06T20:02:42.701Z",
      "isDefault": 0,
      "remark": "speed:614ms",
      "tags": [],
      "priority": 0,
      "proxyMode": "none",
      "customProxy": ""
    },
    {
      "id": "85089410-ecfd-41f5-a39b-f1c94547041b",
      "key": "精品资源",
      "name": "精品资源",
      "api": "https://www.jingpinx.com/api.php/provide/vod",
      "type": 2,
      "isActive": 1,
      "time": "2026-07-06T20:02:42.701Z",
      "isDefault": 0,
      "remark": "speed:621ms",
      "tags": [],
      "priority": 0,
      "proxyMode": "none",
      "customProxy": ""
    },
    {
      "id": "c72388f8-2f05-4419-b195-386dc555a656",
      "key": "非凡资源",
      "name": "非凡资源",
      "api": "http://ffzy5.tv/api.php/provide/vod",
      "type": 2,
      "isActive": 1,
      "time": "2026-07-06T20:02:42.701Z",
      "isDefault": 0,
      "remark": "speed:625ms",
      "tags": [],
      "priority": 0,
      "proxyMode": "none",
      "customProxy": ""
    },
    {
      "id": "56d785a3-84ed-40f9-9c50-93d15118d1d0",
      "key": "茅台资源",
      "name": "茅台资源",
      "api": "https://caiji.maotaizy.cc/api.php/provide/vod",
      "type": 2,
      "isActive": 1,
      "time": "2026-07-06T20:02:42.701Z",
      "isDefault": 0,
      "remark": "speed:661ms",
      "tags": [],
      "priority": 0,
      "proxyMode": "none",
      "customProxy": ""
    },
    {
      "id": "2d9d2b88-e847-4878-9ed2-cebf6d95181e",
      "key": "后台发送接口2字获取最新",
      "name": "后台发送接口2字获取最新",
      "api": "https://mk1080.top/get.txt",
      "type": 2,
      "isActive": 1,
      "time": "2026-07-06T20:02:42.701Z",
      "isDefault": 0,
      "remark": "speed:661ms",
      "tags": [],
      "priority": 0,
      "proxyMode": "none",
      "customProxy": ""
    },
    {
      "id": "78ab8b9e-9b46-4e39-8e03-fdfc21975627",
      "key": "91麻豆",
      "name": "91麻豆",
      "api": "https://91md.me/api.php/provide/vod",
      "type": 2,
      "isActive": 1,
      "time": "2026-07-06T20:02:42.701Z",
      "isDefault": 0,
      "remark": "speed:731ms",
      "tags": [],
      "priority": 0,
      "proxyMode": "none",
      "customProxy": ""
    },
    {
      "id": "c4cc693a-eff6-45ee-bc8d-3f6f399fabdb",
      "key": "🫧韩剧┃蓝光",
      "name": "🫧韩剧┃蓝光",
      "api": "https://16409.kstore.vip/js/hanjukan.json",
      "type": 2,
      "isActive": 1,
      "time": "2026-07-06T20:02:42.701Z",
      "isDefault": 0,
      "remark": "speed:925ms",
      "tags": [],
      "priority": 0,
      "proxyMode": "none",
      "customProxy": ""
    },
    {
      "id": "79fab68c-955f-40c3-9978-6ca93e7c4eb1",
      "key": "魔都动漫",
      "name": "魔都动漫",
      "api": "https://caiji.moduapi.cc/api.php/provide/vod",
      "type": 2,
      "isActive": 1,
      "time": "2026-07-06T20:02:42.701Z",
      "isDefault": 0,
      "remark": "speed:961ms",
      "tags": [],
      "priority": 0,
      "proxyMode": "none",
      "customProxy": ""
    },
    {
      "id": "44853388-5158-45c6-a858-3336600bf977",
      "key": "魔都资源",
      "name": "魔都资源",
      "api": "https://www.mdzyapi.com/api.php/provide/vod",
      "type": 2,
      "isActive": 1,
      "time": "2026-07-06T20:02:42.701Z",
      "isDefault": 0,
      "remark": "speed:975ms",
      "tags": [],
      "priority": 0,
      "proxyMode": "none",
      "customProxy": ""
    },
    {
      "id": "aaf8f0a9-ea35-42e2-a709-0b465c5732e9",
      "key": "非凡采集HTTPS",
      "name": "非凡采集HTTPS",
      "api": "https://cj.ffzyapi.com/api.php/provide/vod",
      "type": 2,
      "isActive": 1,
      "time": "2026-07-06T20:02:42.701Z",
      "isDefault": 0,
      "remark": "speed:1033ms",
      "tags": [],
      "priority": 0,
      "proxyMode": "none",
      "customProxy": ""
    },
    {
      "id": "5a6069c3-8522-48b9-91ae-1452a7259edd",
      "key": "电影天堂",
      "name": "电影天堂",
      "api": "http://caiji.dyttzyapi.com/api.php/provide/vod",
      "type": 2,
      "isActive": 1,
      "time": "2026-07-06T20:02:42.701Z",
      "isDefault": 0,
      "remark": "speed:1112ms",
      "tags": [],
      "priority": 0,
      "proxyMode": "none",
      "customProxy": ""
    },
    {
      "id": "246dfb92-733b-48fb-a816-077577b91908",
      "key": "非凡API",
      "name": "非凡API",
      "api": "https://api.ffzyapi.com/api.php/provide/vod",
      "type": 2,
      "isActive": 1,
      "time": "2026-07-06T20:02:42.701Z",
      "isDefault": 0,
      "remark": "speed:1171ms",
      "tags": [],
      "priority": 0,
      "proxyMode": "none",
      "customProxy": ""
    },
    {
      "id": "8303077f-caaf-4352-9cb2-e65135a7542e",
      "key": "森林资源",
      "name": "森林资源",
      "api": "https://slapibf.com/api.php/provide/vod",
      "type": 2,
      "isActive": 1,
      "time": "2026-07-06T20:02:42.701Z",
      "isDefault": 0,
      "remark": "speed:1204ms",
      "tags": [],
      "priority": 0,
      "proxyMode": "none",
      "customProxy": ""
    },
    {
      "id": "0c48a3c2-56f3-4530-9c01-1542b419b15f",
      "key": "奶香香",
      "name": "奶香香",
      "api": "https://Naixxzy.com/api.php/provide/vod",
      "type": 2,
      "isActive": 1,
      "time": "2026-07-06T20:02:42.701Z",
      "isDefault": 0,
      "remark": "speed:1251ms",
      "tags": [],
      "priority": 0,
      "proxyMode": "none",
      "customProxy": ""
    },
    {
      "id": "577f918a-a0a7-42b7-8d57-7f835548b46e",
      "key": "光速资源",
      "name": "光速资源",
      "api": "https://api.guangsuapi.com/api.php/provide/vod",
      "type": 2,
      "isActive": 1,
      "time": "2026-07-06T20:02:42.701Z",
      "isDefault": 0,
      "remark": "speed:1300ms",
      "tags": [],
      "priority": 0,
      "proxyMode": "none",
      "customProxy": ""
    },
    {
      "id": "ec605756-02e4-45b0-b0eb-ee8b93dd72e1",
      "key": "鲨鱼资源",
      "name": "鲨鱼资源",
      "api": "https://shayuapi.com/api.php/provide/vod",
      "type": 2,
      "isActive": 1,
      "time": "2026-07-06T20:02:42.701Z",
      "isDefault": 0,
      "remark": "speed:1317ms",
      "tags": [],
      "priority": 0,
      "proxyMode": "none",
      "customProxy": ""
    },
    {
      "id": "49838c13-0a73-4035-9e84-eb01a210c332",
      "key": "360资源",
      "name": "360资源",
      "api": "https://360zy.com/api.php/provide/vod",
      "type": 2,
      "isActive": 1,
      "time": "2026-07-06T20:02:42.701Z",
      "isDefault": 0,
      "remark": "speed:1322ms",
      "tags": [],
      "priority": 0,
      "proxyMode": "none",
      "customProxy": ""
    },
    {
      "id": "eb4a0622-8319-44c4-9b5f-e2ebfd482c14",
      "key": "魔都影视",
      "name": "魔都影视",
      "api": "https://www.moduzy.com/api.php/provide/vod",
      "type": 2,
      "isActive": 1,
      "time": "2026-07-06T20:02:42.701Z",
      "isDefault": 0,
      "remark": "speed:1486ms",
      "tags": [],
      "priority": 0,
      "proxyMode": "none",
      "customProxy": ""
    },
    {
      "id": "126ffda5-f843-48da-b18f-03dec7a960c4",
      "key": "奥斯卡资源",
      "name": "奥斯卡资源",
      "api": "https://aosikazy.com/api.php/provide/vod",
      "type": 2,
      "isActive": 1,
      "time": "2026-07-06T20:02:42.701Z",
      "isDefault": 0,
      "remark": "speed:1616ms",
      "tags": [],
      "priority": 0,
      "proxyMode": "none",
      "customProxy": ""
    },
    {
      "id": "9d9ec385-42bb-467c-b8a3-d016024250a8",
      "key": "非凡采集",
      "name": "非凡采集",
      "api": "http://cj.ffzyapi.com/api.php/provide/vod",
      "type": 2,
      "isActive": 1,
      "time": "2026-07-06T20:02:42.701Z",
      "isDefault": 0,
      "remark": "speed:1675ms",
      "tags": [],
      "priority": 0,
      "proxyMode": "none",
      "customProxy": ""
    },
    {
      "id": "5b753444-d069-478d-93b1-8382ca0e26d2",
      "key": "1080JSON",
      "name": "1080JSON",
      "api": "https://api.1080zyku.com/inc/apijson.php",
      "type": 2,
      "isActive": 1,
      "time": "2026-07-06T20:02:42.701Z",
      "isDefault": 0,
      "remark": "speed:1792ms",
      "tags": [],
      "priority": 0,
      "proxyMode": "none",
      "customProxy": ""
    },
    {
      "id": "0ad9e667-907b-44dd-8366-acb2e108cd6b",
      "key": "如意资源",
      "name": "如意资源",
      "api": "https://cj.rycjapi.com/api.php/provide/vod",
      "type": 2,
      "isActive": 1,
      "time": "2026-07-06T20:02:42.701Z",
      "isDefault": 0,
      "remark": "speed:1795ms",
      "tags": [],
      "priority": 0,
      "proxyMode": "none",
      "customProxy": ""
    },
    {
      "id": "e832ef6a-c243-4590-92bf-1a295876a222",
      "key": "速博资源",
      "name": "速博资源",
      "api": "https://subocaiji.com/api.php/provide/vod",
      "type": 2,
      "isActive": 1,
      "time": "2026-07-06T20:02:42.701Z",
      "isDefault": 0,
      "remark": "speed:2106ms",
      "tags": [],
      "priority": 0,
      "proxyMode": "none",
      "customProxy": ""
    },
    {
      "id": "bdc5ece2-3133-4c25-bf49-2362fe78a6c4",
      "key": "暴风资源",
      "name": "暴风资源",
      "api": "https://bfzyapi.com/api.php/provide/vod",
      "type": 2,
      "isActive": 1,
      "time": "2026-07-06T20:02:42.701Z",
      "isDefault": 0,
      "remark": "speed:2991ms",
      "tags": [],
      "priority": 0,
      "proxyMode": "none",
      "customProxy": ""
    }
  ]
}